svfsc.cpython-38-darwin.so
svfsc-0.4.1.dist-info/LICENSE
svfsc-0.4.1.dist-info/METADATA
svfsc-0.4.1.dist-info/WHEEL
svfsc-0.4.1.dist-info/top_level.txt
svfsc-0.4.1.dist-info/RECORD
