Metadata-Version: 2.1
Name: svfsc
Version: 0.4.1
Summary: Sparse Virtual File System Cache implemented in C++.
Home-page: https://github.com/paulross/svfsc
Author: Paul Ross
Author-email: apaulross@gmail.com
License: MIT License
Keywords: svf,svfs,svfsc
Classifier: Development Status :: 5 - Production/Stable
Classifier: Intended Audience :: Developers
Classifier: License :: OSI Approved :: MIT License
Classifier: Natural Language :: English
Classifier: Operating System :: OS Independent
Classifier: Programming Language :: C++
Classifier: Programming Language :: Python :: 3
Classifier: Programming Language :: Python :: 3.8
Classifier: Programming Language :: Python :: 3.9
Classifier: Programming Language :: Python :: 3.10
Classifier: Programming Language :: Python :: 3.11
Classifier: Programming Language :: Python :: 3.12
Classifier: Programming Language :: Python :: 3.13
Classifier: Topic :: Software Development :: Libraries
License-File: LICENSE
